{
  "annotations": {
    "list": [
      {
        "builtIn": 1,
        "datasource": {
          "type": "datasource",
          "uid": "grafana"
        },
        "enable": true,
        "hide": true,
        "iconColor": "rgba(0, 211, 255, 1)",
        "name": "Annotations & Alerts",
        "target": {
          "limit": 100,
          "matchAny": false,
          "tags": [],
          "type": "dashboard"
        },
        "type": "dashboard"
      }
    ]
  },
  "editable": false,
  "fiscalYearStartMonth": 0,
  "graphTooltip": 2,
  "id": 36,
  "iteration": 1702301893505,
  "links": [],
  "liveNow": false,
  "panels": [
    {
      "collapsed": false,
      "datasource": {
        "type": "prometheus",
        "uid": "P0D6E4079E36703EB"
      },
      "gridPos": {
        "h": 1,
        "w": 24,
        "x": 0,
        "y": 0
      },
      "id": 33,
      "panels": [],
      "title": "LINSTOR",
      "type": "row"
    },
    {
      "datasource": {
        "uid": "${ds_prometheus}"
      },
      "description": "",
      "fieldConfig": {
        "defaults": {
          "color": {
            "mode": "thresholds"
          },
          "mappings": [],
          "thresholds": {
            "mode": "absolute",
            "steps": [
              {
                "color": "green",
                "value": null
              }
            ]
          }
        },
        "overrides": []
      },
      "gridPos": {
        "h": 3,
        "w": 3,
        "x": 0,
        "y": 1
      },
      "id": 36,
      "options": {
        "colorMode": "value",
        "graphMode": "none",
        "justifyMode": "auto",
        "orientation": "auto",
        "reduceOptions": {
          "calcs": [
            "lastNotNull"
          ],
          "fields": "",
          "values": false
        },
        "text": {},
        "textMode": "auto"
      },
      "pluginVersion": "8.5.13",
      "targets": [
        {
          "exemplar": true,
          "expr": "count(linstor_node_state{nodetype=\"SATELLITE\",node=~\"$node\"} == 2) OR on() vector(0)",
          "legendFormat": "",
          "refId": "A"
        }
      ],
      "title": "Nodes",
      "type": "stat"
    },
    {
      "datasource": {
        "uid": "${ds_prometheus}"
      },
      "description": "",
      "fieldConfig": {
        "defaults": {
          "color": {
            "mode": "thresholds"
          },
          "mappings": [],
          "thresholds": {
            "mode": "absolute",
            "steps": [
              {
                "color": "green",
                "value": null
              }
            ]
          }
        },
        "overrides": []
      },
      "gridPos": {
        "h": 3,
        "w": 3,
        "x": 3,
        "y": 1
      },
      "id": 38,
      "options": {
        "colorMode": "value",
        "graphMode": "none",
        "justifyMode": "auto",
        "orientation": "auto",
        "reduceOptions": {
          "calcs": [
            "lastNotNull"
          ],
          "fields": "",
          "values": false
        },
        "text": {},
        "textMode": "auto"
      },
      "pluginVersion": "8.5.13",
      "targets": [
        {
          "exemplar": true,
          "expr": "count(linstor_storage_pool_capacity_total_bytes{driver!=\"DISKLESS\",node=~\"$node\"}) OR on() vector(0)",
          "legendFormat": "",
          "refId": "A"
        }
      ],
      "title": "Storage Pools",
      "type": "stat"
    },
    {
      "datasource": {
        "uid": "${ds_prometheus}"
      },
      "description": "",
      "fieldConfig": {
        "defaults": {
          "color": {
            "mode": "thresholds"
          },
          "mappings": [],
          "thresholds": {
            "mode": "absolute",
            "steps": [
              {
                "color": "green",
                "value": null
              }
            ]
          }
        },
        "overrides": []
      },
      "gridPos": {
        "h": 3,
        "w": 3,
        "x": 6,
        "y": 1
      },
      "id": 35,
      "options": {
        "colorMode": "value",
        "graphMode": "none",
        "justifyMode": "auto",
        "orientation": "auto",
        "reduceOptions": {
          "calcs": [
            "lastNotNull"
          ],
          "fields": "",
          "values": false
        },
        "text": {},
        "textMode": "auto"
      },
      "pluginVersion": "8.5.13",
      "targets": [
        {
          "exemplar": true,
          "expr": "sum(linstor_resource_definition_count{}) OR on() vector(0)",
          "legendFormat": "",
          "refId": "A"
        }
      ],
      "title": "Resource Definitions",
      "type": "stat"
    },
    {
      "datasource": {
        "uid": "${ds_prometheus}"
      },
      "description": "",
      "fieldConfig": {
        "defaults": {
          "color": {
            "mode": "thresholds"
          },
          "mappings": [],
          "thresholds": {
            "mode": "absolute",
            "steps": [
              {
                "color": "green",
                "value": null
              }
            ]
          }
        },
        "overrides": []
      },
      "gridPos": {
        "h": 3,
        "w": 3,
        "x": 9,
        "y": 1
      },
      "id": 37,
      "options": {
        "colorMode": "value",
        "graphMode": "none",
        "justifyMode": "auto",
        "orientation": "auto",
        "reduceOptions": {
          "calcs": [
            "lastNotNull"
          ],
          "fields": "",
          "values": false
        },
        "text": {},
        "textMode": "auto"
      },
      "pluginVersion": "8.5.13",
      "targets": [
        {
          "exemplar": true,
          "expr": "count(linstor_resource_state) OR on() vector(0)",
          "legendFormat": "",
          "refId": "A"
        }
      ],
      "title": "Resources",
      "type": "stat"
    },
    {
      "datasource": {
        "uid": "${ds_prometheus}"
      },
      "fieldConfig": {
        "defaults": {
          "color": {
            "mode": "thresholds"
          },
          "mappings": [],
          "max": 100,
          "thresholds": {
            "mode": "absolute",
            "steps": [
              {
                "color": "green",
                "value": null
              },
              {
                "color": "red",
                "value": 80
              }
            ]
          },
          "unit": "percent"
        },
        "overrides": []
      },
      "gridPos": {
        "h": 9,
        "w": 6,
        "x": 12,
        "y": 1
      },
      "id": 41,
      "options": {
        "orientation": "auto",
        "reduceOptions": {
          "calcs": [
            "lastNotNull"
          ],
          "fields": "",
          "values": false
        },
        "showThresholdLabels": false,
        "showThresholdMarkers": true,
        "text": {}
      },
      "pluginVersion": "8.5.13",
      "targets": [
        {
          "exemplar": true,
          "expr": "((sum by (storage_pool)(linstor_storage_pool_capacity_total_bytes != 0)-sum by (storage_pool)(linstor_storage_pool_capacity_free_bytes))*100/sum by (storage_pool)(linstor_storage_pool_capacity_total_bytes))",
          "hide": false,
          "legendFormat": "{{ storage_pool }}",
          "refId": "A"
        }
      ],
      "title": "Space Usage",
      "type": "gauge"
    },
    {
      "datasource": {
        "uid": "${ds_prometheus}"
      },
      "fieldConfig": {
        "defaults": {
          "color": {
            "mode": "thresholds"
          },
          "mappings": [],
          "thresholds": {
            "mode": "absolute",
            "steps": [
              {
                "color": "text",
                "value": null
              }
            ]
          },
          "unit": "bytes"
        },
        "overrides": []
      },
      "gridPos": {
        "h": 3,
        "w": 6,
        "x": 18,
        "y": 1
      },
      "id": 43,
      "options": {
        "colorMode": "value",
        "graphMode": "none",
        "justifyMode": "auto",
        "orientation": "auto",
        "reduceOptions": {
          "calcs": [
            "lastNotNull"
          ],
          "fields": "",
          "values": false
        },
        "text": {},
        "textMode": "auto"
      },
      "pluginVersion": "8.5.13",
      "targets": [
        {
          "exemplar": true,
          "expr": "sum by (storage_pool) (linstor_storage_pool_capacity_total_bytes != 0)",
          "hide": false,
          "legendFormat": "{{ storage_pool }}",
          "refId": "A"
        }
      ],
      "title": "Total",
      "type": "stat"
    },
    {
      "datasource": {
        "uid": "${ds_prometheus}"
      },
      "description": "",
      "fieldConfig": {
        "defaults": {
          "color": {
            "mode": "thresholds"
          },
          "mappings": [],
          "thresholds": {
            "mode": "absolute",
            "steps": [
              {
                "color": "green",
                "value": null
              },
              {
                "color": "red",
                "value": 1
              }
            ]
          }
        },
        "overrides": []
      },
      "gridPos": {
        "h": 3,
        "w": 4,
        "x": 0,
        "y": 4
      },
      "id": 51,
      "options": {
        "colorMode": "background",
        "graphMode": "none",
        "justifyMode": "auto",
        "orientation": "auto",
        "reduceOptions": {
          "calcs": [
            "lastNotNull"
          ],
          "fields": "",
          "values": false
        },
        "text": {},
        "textMode": "auto"
      },
      "pluginVersion": "8.5.13",
      "targets": [
        {
          "exemplar": true,
          "expr": "count(linstor_node_state{nodetype=\"SATELLITE\", node=~\"$node\"} != 2) OR on() vector(0)",
          "legendFormat": "",
          "refId": "A"
        }
      ],
      "title": "Offline Nodes",
      "type": "stat"
    },
    {
      "datasource": {
        "uid": "${ds_prometheus}"
      },
      "description": "",
      "fieldConfig": {
        "defaults": {
          "color": {
            "mode": "thresholds"
          },
          "mappings": [],
          "thresholds": {
            "mode": "absolute",
            "steps": [
              {
                "color": "green",
                "value": null
              },
              {
                "color": "red",
                "value": 1
              }
            ]
          }
        },
        "overrides": []
      },
      "gridPos": {
        "h": 3,
        "w": 4,
        "x": 4,
        "y": 4
      },
      "id": 50,
      "options": {
        "colorMode": "background",
        "graphMode": "none",
        "justifyMode": "auto",
        "orientation": "auto",
        "reduceOptions": {
          "calcs": [
            "lastNotNull"
          ],
          "fields": "",
          "values": false
        },
        "text": {},
        "textMode": "auto"
      },
      "pluginVersion": "8.5.13",
      "targets": [
        {
          "exemplar": true,
          "expr": "count(linstor_storage_pool_error_count{driver!=\"DISKLESS\", node=~\"$node\"} != 0) OR on() vector(0)",
          "legendFormat": "",
          "refId": "A"
        }
      ],
      "title": "Failed Storage Pools",
      "type": "stat"
    },
    {
      "datasource": {
        "type": "prometheus",
        "uid": "${ds_prometheus}"
      },
      "description": "",
      "fieldConfig": {
        "defaults": {
          "color": {
            "mode": "thresholds"
          },
          "mappings": [],
          "thresholds": {
            "mode": "absolute",
            "steps": [
              {
                "color": "green",
                "value": null
              },
              {
                "color": "red",
                "value": 1
              }
            ]
          }
        },
        "overrides": []
      },
      "gridPos": {
        "h": 3,
        "w": 4,
        "x": 8,
        "y": 4
      },
      "id": 49,
      "options": {
        "colorMode": "background",
        "graphMode": "none",
        "justifyMode": "auto",
        "orientation": "auto",
        "reduceOptions": {
          "calcs": [
            "lastNotNull"
          ],
          "fields": "",
          "values": false
        },
        "text": {},
        "textMode": "auto"
      },
      "pluginVersion": "8.5.13",
      "targets": [
        {
          "datasource": {
            "type": "prometheus",
            "uid": "P0D6E4079E36703EB"
          },
          "exemplar": true,
          "expr": "count((linstor_volume_state != 1) != 4) OR on() vector(0)",
          "legendFormat": "",
          "refId": "A"
        }
      ],
      "title": "Failed Resources",
      "type": "stat"
    },
    {
      "datasource": {
        "uid": "${ds_prometheus}"
      },
      "description": "",
      "fieldConfig": {
        "defaults": {
          "color": {
            "mode": "thresholds"
          },
          "mappings": [],
          "thresholds": {
            "mode": "absolute",
            "steps": [
              {
                "color": "dark-green",
                "value": null
              }
            ]
          },
          "unit": "bytes"
        },
        "overrides": []
      },
      "gridPos": {
        "h": 3,
        "w": 6,
        "x": 18,
        "y": 4
      },
      "id": 44,
      "options": {
        "colorMode": "value",
        "graphMode": "none",
        "justifyMode": "auto",
        "orientation": "auto",
        "reduceOptions": {
          "calcs": [
            "lastNotNull"
          ],
          "fields": "",
          "values": false
        },
        "text": {},
        "textMode": "auto"
      },
      "pluginVersion": "8.5.13",
      "targets": [
        {
          "exemplar": true,
          "expr": "sum by (storage_pool) (linstor_storage_pool_capacity_free_bytes != 0)",
          "hide": false,
          "legendFormat": "{{ storage_pool }}",
          "refId": "A"
        }
      ],
      "title": "Free",
      "type": "stat"
    },
    {
      "datasource": {
        "uid": "${ds_prometheus}"
      },
      "description": "",
      "fieldConfig": {
        "defaults": {
          "color": {
            "mode": "thresholds"
          },
          "mappings": [],
          "thresholds": {
            "mode": "absolute",
            "steps": [
              {
                "color": "green",
                "value": null
              },
              {
                "color": "dark-yellow",
                "value": 6
              },
              {
                "color": "orange",
                "value": 10
              },
              {
                "color": "red",
                "value": 20
              }
            ]
          }
        },
        "overrides": []
      },
      "gridPos": {
        "h": 3,
        "w": 12,
        "x": 0,
        "y": 7
      },
      "id": 52,
      "options": {
        "colorMode": "background",
        "graphMode": "none",
        "justifyMode": "auto",
        "orientation": "horizontal",
        "reduceOptions": {
          "calcs": [
            "lastNotNull"
          ],
          "fields": "",
          "values": false
        },
        "text": {},
        "textMode": "auto"
      },
      "pluginVersion": "8.5.13",
      "targets": [
        {
          "exemplar": true,
          "expr": "sum by (module) (round(increase(linstor_error_reports_count{module!=\"\", node=~\"$node\"}[$__interval_sx4])))",
          "instant": false,
          "legendFormat": "{{ module }}",
          "refId": "A"
        }
      ],
      "title": "New Error Reports",
      "transformations": [],
      "type": "stat"
    },
    {
      "datasource": {
        "uid": "${ds_prometheus}"
      },
      "fieldConfig": {
        "defaults": {
          "color": {
            "mode": "thresholds"
          },
          "mappings": [],
          "thresholds": {
            "mode": "absolute",
            "steps": [
              {
                "color": "dark-red",
                "value": null
              }
            ]
          },
          "unit": "bytes"
        },
        "overrides": []
      },
      "gridPos": {
        "h": 3,
        "w": 6,
        "x": 18,
        "y": 7
      },
      "id": 42,
      "options": {
        "colorMode": "value",
        "graphMode": "none",
        "justifyMode": "auto",
        "orientation": "auto",
        "reduceOptions": {
          "calcs": [
            "lastNotNull"
          ],
          "fields": "",
          "values": false
        },
        "text": {},
        "textMode": "auto"
      },
      "pluginVersion": "8.5.13",
      "targets": [
        {
          "exemplar": true,
          "expr": "sum by (storage_pool) ((linstor_storage_pool_capacity_total_bytes != 0) - (linstor_storage_pool_capacity_free_bytes != 0))",
          "hide": false,
          "legendFormat": "{{ storage_pool }}",
          "refId": "A"
        }
      ],
      "title": "Used",
      "type": "stat"
    },
    {
      "datasource": {
        "uid": "${ds_prometheus}"
      },
      "fieldConfig": {
        "defaults": {
          "color": {
            "mode": "palette-classic"
          },
          "custom": {
            "axisLabel": "",
            "axisPlacement": "auto",
            "barAlignment": 0,
            "drawStyle": "line",
            "fillOpacity": 57,
            "gradientMode": "none",
            "hideFrom": {
              "legend": false,
              "tooltip": false,
              "viz": false
            },
            "lineInterpolation": "linear",
            "lineWidth": 1,
            "pointSize": 5,
            "scaleDistribution": {
              "type": "linear"
            },
            "showPoints": "auto",
            "spanNulls": false,
            "stacking": {
              "group": "A",
              "mode": "none"
            },
            "thresholdsStyle": {
              "mode": "off"
            }
          },
          "mappings": [],
          "thresholds": {
            "mode": "absolute",
            "steps": [
              {
                "color": "text",
                "value": null
              }
            ]
          },
          "unit": "pps"
        },
        "overrides": []
      },
      "gridPos": {
        "h": 8,
        "w": 24,
        "x": 0,
        "y": 10
      },
      "id": 40,
      "options": {
        "legend": {
          "calcs": [],
          "displayMode": "list",
          "placement": "bottom"
        },
        "tooltip": {
          "mode": "single",
          "sort": "none"
        }
      },
      "pluginVersion": "8.2.6",
      "targets": [
        {
          "exemplar": true,
          "expr": "avg_over_time(linstor_scrape_duration_seconds[$__interval_sx3])",
          "legendFormat": "allocated",
          "refId": "A"
        }
      ],
      "title": "Scrape Duration",
      "type": "timeseries"
    },
    {
      "datasource": {
        "type": "prometheus",
        "uid": "${ds_prometheus}"
      },
      "fieldConfig": {
        "defaults": {
          "color": {
            "mode": "thresholds"
          },
          "custom": {
            "align": "auto",
            "displayMode": "auto",
            "filterable": false,
            "inspect": false
          },
          "mappings": [
            {
              "options": {
                "1": {
                  "index": 1,
                  "text": "UpToDate"
                },
                "2": {
                  "index": 2,
                  "text": "Created"
                },
                "3": {
                  "index": 3,
                  "text": "Attached"
                },
                "4": {
                  "index": 4,
                  "text": "Diskless"
                },
                "5": {
                  "index": 5,
                  "text": "Inconsistent"
                },
                "6": {
                  "index": 6,
                  "text": "Failed"
                },
                "7": {
                  "index": 7,
                  "text": "To: Creating"
                },
                "8": {
                  "index": 8,
                  "text": "To: Attachable"
                },
                "9": {
                  "index": 9,
                  "text": "To: Attaching"
                },
                "90": {
                  "index": 10,
                  "text": "Diskless(Detached)"
                },
                "-1": {
                  "index": 0,
                  "text": "DUnknown"
                }
              },
              "type": "value"
            }
          ],
          "thresholds": {
            "mode": "absolute",
            "steps": [
              {
                "color": "green",
                "value": null
              },
              {
                "color": "red",
                "value": 1
              }
            ]
          }
        },
        "overrides": [
          {
            "matcher": {
              "id": "byName",
              "options": "Node"
            },
            "properties": [
              {
                "id": "custom.width"
              }
            ]
          },
          {
            "matcher": {
              "id": "byName",
              "options": "resource"
            },
            "properties": [
              {
                "id": "custom.width",
                "value": 330
              }
            ]
          },
          {
            "matcher": {
              "id": "byName",
              "options": "Status"
            },
            "properties": [
              {
                "id": "custom.width"
              },
              {
                "id": "custom.minWidth",
                "value": 98
              }
            ]
          }
        ]
      },
      "gridPos": {
        "h": 8,
        "w": 12,
        "x": 0,
        "y": 18
      },
      "id": 54,
      "options": {
        "footer": {
          "fields": "",
          "reducer": [
            "sum"
          ],
          "show": false
        },
        "frameIndex": 0,
        "showHeader": true,
        "sortBy": []
      },
      "pluginVersion": "8.5.13",
      "targets": [
        {
          "datasource": {
            "type": "prometheus",
            "uid": "P0D6E4079E36703EB"
          },
          "editorMode": "code",
          "exemplar": false,
          "expr": "max by (node, resource) ((linstor_volume_state != 1) != 4)",
          "format": "table",
          "instant": true,
          "intervalFactor": 1,
          "legendFormat": "",
          "range": false,
          "refId": "A"
        }
      ],
      "title": "Linstor Volumes not happen",
      "transformations": [
        {
          "id": "merge",
          "options": {}
        },
        {
          "id": "organize",
          "options": {
            "excludeByName": {
              "Time": true,
              "Value": false
            },
            "indexByName": {},
            "renameByName": {
              "Value": "Status",
              "Value #A": "Quorum?",
              "instance": "Instance",
              "name": "DRBD Resource",
              "node": "Node"
            }
          }
        }
      ],
      "type": "table"
    },
    {
      "datasource": {
        "type": "prometheus",
        "uid": "${ds_prometheus}"
      },
      "fieldConfig": {
        "defaults": {
          "color": {
            "mode": "thresholds"
          },
          "custom": {
            "align": "auto",
            "displayMode": "auto",
            "filterable": false,
            "inspect": false
          },
          "mappings": [
            {
              "options": {
                "0": {
                  "index": 1,
                  "text": "secondary"
                },
                "1": {
                  "index": 2,
                  "text": "primary"
                },
                "-1": {
                  "index": 0,
                  "text": "Unknown"
                }
              },
              "type": "value"
            }
          ],
          "thresholds": {
            "mode": "absolute",
            "steps": [
              {
                "color": "green",
                "value": null
              },
              {
                "color": "red",
                "value": 1
              }
            ]
          }
        },
        "overrides": [
          {
            "matcher": {
              "id": "byName",
              "options": "Node"
            },
            "properties": [
              {
                "id": "custom.width",
                "value": 230
              }
            ]
          },
          {
            "matcher": {
              "id": "byName",
              "options": "resource"
            },
            "properties": [
              {
                "id": "custom.width"
              }
            ]
          },
          {
            "matcher": {
              "id": "byName",
              "options": "Status"
            },
            "properties": [
              {
                "id": "custom.width",
                "value": 128
              }
            ]
          }
        ]
      },
      "gridPos": {
        "h": 8,
        "w": 12,
        "x": 12,
        "y": 18
      },
      "id": 55,
      "options": {
        "footer": {
          "fields": "",
          "reducer": [
            "sum"
          ],
          "show": false
        },
        "frameIndex": 0,
        "showHeader": true,
        "sortBy": []
      },
      "pluginVersion": "8.5.13",
      "targets": [
        {
          "datasource": {
            "type": "prometheus",
            "uid": "P0D6E4079E36703EB"
          },
          "editorMode": "code",
          "exemplar": false,
          "expr": "max by (node, resource) (linstor_resource_state == -1)",
          "format": "table",
          "instant": true,
          "intervalFactor": 1,
          "legendFormat": "",
          "range": false,
          "refId": "A"
        }
      ],
      "title": "Linstor Resources not happen",
      "transformations": [
        {
          "id": "merge",
          "options": {}
        },
        {
          "id": "organize",
          "options": {
            "excludeByName": {
              "Time": true,
              "Value": false
            },
            "indexByName": {},
            "renameByName": {
              "Value": "Status",
              "Value #A": "Quorum?",
              "instance": "Instance",
              "name": "DRBD Resource",
              "node": "Node"
            }
          }
        }
      ],
      "type": "table"
    },
    {
      "collapsed": false,
      "datasource": {
        "type": "prometheus",
        "uid": "P0D6E4079E36703EB"
      },
      "gridPos": {
        "h": 1,
        "w": 24,
        "x": 0,
        "y": 26
      },
      "id": 46,
      "panels": [],
      "title": "Statistics",
      "type": "row"
    },
    {
      "aliasColors": {},
      "bars": false,
      "dashLength": 10,
      "dashes": false,
      "datasource": {
        "uid": "${ds_prometheus}"
      },
      "fieldConfig": {
        "defaults": {
          "unit": "binBps"
        },
        "overrides": []
      },
      "fill": 1,
      "fillGradient": 0,
      "gridPos": {
        "h": 8,
        "w": 12,
        "x": 0,
        "y": 27
      },
      "hiddenSeries": false,
      "id": 24,
      "legend": {
        "avg": false,
        "current": false,
        "max": false,
        "min": false,
        "show": true,
        "total": false,
        "values": false
      },
      "lines": true,
      "linewidth": 1,
      "nullPointMode": "null",
      "options": {
        "alertThreshold": false
      },
      "percentage": false,
      "pluginVersion": "8.5.13",
      "pointradius": 2,
      "points": false,
      "renderer": "flot",
      "seriesOverrides": [],
      "spaceLength": 10,
      "stack": false,
      "steppedLine": true,
      "targets": [
        {
          "exemplar": true,
          "expr": "rate(drbd_device_written_bytes_total[$__interval_sx3]) and topk(5, avg_over_time(drbd_device_written_bytes_total[$__interval_sx3]) > 0)",
          "instant": false,
          "legendFormat": "{{name}} on {{node}}",
          "refId": "A"
        }
      ],
      "thresholds": [],
      "timeRegions": [],
      "title": "Write Rate (5 Most Active Volumes)",
      "tooltip": {
        "shared": true,
        "sort": 0,
        "value_type": "individual"
      },
      "type": "graph",
      "xaxis": {
        "mode": "time",
        "show": true,
        "values": []
      },
      "yaxes": [
        {
          "$$hashKey": "object:104",
          "format": "binBps",
          "logBase": 1,
          "show": true
        },
        {
          "$$hashKey": "object:105",
          "format": "short",
          "logBase": 1,
          "show": true
        }
      ],
      "yaxis": {
        "align": false
      }
    },
    {
      "aliasColors": {},
      "bars": false,
      "dashLength": 10,
      "dashes": false,
      "datasource": {
        "uid": "${ds_prometheus}"
      },
      "fieldConfig": {
        "defaults": {
          "unit": "binBps"
        },
        "overrides": []
      },
      "fill": 1,
      "fillGradient": 0,
      "gridPos": {
        "h": 8,
        "w": 12,
        "x": 12,
        "y": 27
      },
      "hiddenSeries": false,
      "id": 25,
      "legend": {
        "avg": false,
        "current": false,
        "max": false,
        "min": false,
        "show": true,
        "total": false,
        "values": false
      },
      "lines": true,
      "linewidth": 1,
      "nullPointMode": "null",
      "options": {
        "alertThreshold": false
      },
      "percentage": false,
      "pluginVersion": "8.5.13",
      "pointradius": 2,
      "points": false,
      "renderer": "flot",
      "seriesOverrides": [],
      "spaceLength": 10,
      "stack": false,
      "steppedLine": true,
      "targets": [
        {
          "exemplar": true,
          "expr": "rate(drbd_device_read_bytes_total[$__interval_sx3]) and topk(5, avg_over_time(drbd_device_read_bytes_total[$__interval_sx3]) > 0)",
          "instant": false,
          "legendFormat": "{{name}} on {{node}}",
          "refId": "A"
        }
      ],
      "thresholds": [],
      "timeRegions": [],
      "title": "Read Rate (5 Most Active Volumes)",
      "tooltip": {
        "shared": true,
        "sort": 0,
        "value_type": "individual"
      },
      "type": "graph",
      "xaxis": {
        "mode": "time",
        "show": true,
        "values": []
      },
      "yaxes": [
        {
          "$$hashKey": "object:254",
          "format": "binBps",
          "logBase": 1,
          "show": true
        },
        {
          "$$hashKey": "object:255",
          "format": "short",
          "logBase": 1,
          "show": true
        }
      ],
      "yaxis": {
        "align": false
      }
    },
    {
      "collapsed": false,
      "datasource": {
        "uid": "${ds_prometheus}"
      },
      "gridPos": {
        "h": 1,
        "w": 24,
        "x": 0,
        "y": 35
      },
      "id": 8,
      "panels": [],
      "title": "DRBD",
      "type": "row"
    },
    {
      "aliasColors": {},
      "bars": false,
      "dashLength": 10,
      "dashes": false,
      "datasource": {
        "type": "prometheus",
        "uid": "${ds_prometheus}"
      },
      "fieldConfig": {
        "defaults": {
          "unit": "s"
        },
        "overrides": []
      },
      "fill": 1,
      "fillGradient": 0,
      "gridPos": {
        "h": 8,
        "w": 24,
        "x": 0,
        "y": 36
      },
      "hiddenSeries": false,
      "id": 27,
      "legend": {
        "avg": false,
        "current": false,
        "max": false,
        "min": false,
        "show": true,
        "total": false,
        "values": false
      },
      "lines": true,
      "linewidth": 1,
      "nullPointMode": "null",
      "options": {
        "alertThreshold": false
      },
      "percentage": false,
      "pluginVersion": "8.5.13",
      "pointradius": 2,
      "points": false,
      "renderer": "flot",
      "seriesOverrides": [],
      "spaceLength": 10,
      "stack": false,
      "steppedLine": true,
      "targets": [
        {
          "datasource": {
            "type": "prometheus",
            "uid": "P0D6E4079E36703EB"
          },
          "editorMode": "code",
          "exemplar": true,
          "expr": "avg_over_time(scrape_duration_seconds{job=\"linstor-node\"}[$__interval_sx3])",
          "legendFormat": "{{node}}",
          "range": true,
          "refId": "A"
        }
      ],
      "thresholds": [],
      "timeRegions": [],
      "title": "Scrape Duration",
      "tooltip": {
        "shared": true,
        "sort": 0,
        "value_type": "individual"
      },
      "type": "graph",
      "xaxis": {
        "mode": "time",
        "show": true,
        "values": []
      },
      "yaxes": [
        {
          "$$hashKey": "object:158",
          "format": "s",
          "logBase": 1,
          "show": true
        },
        {
          "$$hashKey": "object:159",
          "format": "short",
          "logBase": 1,
          "show": true
        }
      ],
      "yaxis": {
        "align": false
      }
    },
    {
      "datasource": {
        "type": "prometheus",
        "uid": "${ds_prometheus}"
      },
      "fieldConfig": {
        "defaults": {
          "color": {
            "mode": "thresholds"
          },
          "mappings": [],
          "thresholds": {
            "mode": "absolute",
            "steps": [
              {
                "color": "green",
                "value": null
              }
            ]
          }
        },
        "overrides": []
      },
      "gridPos": {
        "h": 13,
        "w": 24,
        "x": 0,
        "y": 44
      },
      "id": 6,
      "links": [],
      "maxDataPoints": 100,
      "options": {
        "orientation": "auto",
        "reduceOptions": {
          "calcs": [
            "lastNotNull"
          ],
          "fields": "",
          "values": false
        },
        "showThresholdLabels": false,
        "showThresholdMarkers": true,
        "text": {}
      },
      "pluginVersion": "8.5.13",
      "targets": [
        {
          "$$hashKey": "object:470",
          "aggregation": "Last",
          "datasource": {
            "type": "prometheus",
            "uid": "P0D6E4079E36703EB"
          },
          "decimals": 2,
          "displayAliasType": "Warning / Critical",
          "displayType": "Regular",
          "displayValueWithAlias": "Never",
          "editorMode": "code",
          "exemplar": true,
          "expr": "drbd_resource_resources",
          "legendFormat": "{{node}}",
          "range": true,
          "refId": "A",
          "units": "none",
          "valueHandler": "Number Threshold"
        }
      ],
      "title": "Number of DRBD Resources",
      "type": "gauge"
    },
    {
      "datasource": {
        "uid": "${ds_prometheus}"
      },
      "fieldConfig": {
        "defaults": {
          "color": {
            "mode": "thresholds"
          },
          "mappings": [],
          "thresholds": {
            "mode": "absolute",
            "steps": [
              {
                "color": "green",
                "value": null
              },
              {
                "color": "red",
                "value": 1
              }
            ]
          }
        },
        "overrides": []
      },
      "gridPos": {
        "h": 3,
        "w": 4,
        "x": 0,
        "y": 57
      },
      "id": 14,
      "options": {
        "colorMode": "background",
        "graphMode": "none",
        "justifyMode": "auto",
        "orientation": "auto",
        "reduceOptions": {
          "calcs": [
            "lastNotNull"
          ],
          "fields": "",
          "values": false
        },
        "text": {},
        "textMode": "auto"
      },
      "pluginVersion": "8.5.13",
      "targets": [
        {
          "exemplar": false,
          "expr": "count(count by (name) (drbd_connection_state{drbd_connection_state!=\"UpToDate\", drbd_connection_state!=\"Connected\", node=~\"$node\"} == 1)) OR on() vector(0)",
          "legendFormat": "",
          "refId": "A"
        }
      ],
      "title": "disconnected",
      "type": "stat"
    },
    {
      "datasource": {
        "uid": "${ds_prometheus}"
      },
      "fieldConfig": {
        "defaults": {
          "color": {
            "mode": "thresholds"
          },
          "mappings": [
            {
              "options": {
                "match": "null",
                "result": {
                  "index": 0,
                  "text": "0"
                }
              },
              "type": "special"
            }
          ],
          "thresholds": {
            "mode": "absolute",
            "steps": [
              {
                "color": "green",
                "value": null
              },
              {
                "color": "orange",
                "value": 1
              }
            ]
          }
        },
        "overrides": []
      },
      "gridPos": {
        "h": 3,
        "w": 4,
        "x": 4,
        "y": 57
      },
      "id": 20,
      "options": {
        "colorMode": "background",
        "graphMode": "none",
        "justifyMode": "auto",
        "orientation": "auto",
        "reduceOptions": {
          "calcs": [
            "lastNotNull"
          ],
          "fields": "",
          "values": false
        },
        "text": {},
        "textMode": "auto"
      },
      "pluginVersion": "8.5.13",
      "targets": [
        {
          "exemplar": true,
          "expr": "count(count by (name) (drbd_device_quorum == 0)) OR on() vector(0)",
          "format": "time_series",
          "instant": false,
          "intervalFactor": 1,
          "legendFormat": "",
          "refId": "A"
        },
        {
          "exemplar": true,
          "expr": "count(drbd_device_quorum == 0)",
          "hide": true,
          "legendFormat": "",
          "refId": "B"
        }
      ],
      "title": "without quorum",
      "type": "stat"
    },
    {
      "datasource": {
        "uid": "${ds_prometheus}"
      },
      "description": "",
      "fieldConfig": {
        "defaults": {
          "color": {
            "mode": "thresholds"
          },
          "mappings": [],
          "thresholds": {
            "mode": "absolute",
            "steps": [
              {
                "color": "green",
                "value": null
              },
              {
                "color": "red",
                "value": 1
              }
            ]
          }
        },
        "overrides": []
      },
      "gridPos": {
        "h": 3,
        "w": 4,
        "x": 8,
        "y": 57
      },
      "id": 4,
      "options": {
        "colorMode": "background",
        "graphMode": "none",
        "justifyMode": "auto",
        "orientation": "auto",
        "reduceOptions": {
          "calcs": [
            "lastNotNull"
          ],
          "fields": "",
          "values": false
        },
        "text": {},
        "textMode": "auto"
      },
      "pluginVersion": "8.5.13",
      "targets": [
        {
          "exemplar": true,
          "expr": "count(drbd_device_unintentionaldiskless == 1) OR on() vector(0)",
          "legendFormat": "",
          "refId": "A"
        }
      ],
      "title": "storage failure",
      "type": "stat"
    },
    {
      "datasource": {
        "uid": "${ds_prometheus}"
      },
      "description": "DRBD data out of sync with a peer",
      "fieldConfig": {
        "defaults": {
          "color": {
            "mode": "thresholds"
          },
          "mappings": [],
          "thresholds": {
            "mode": "absolute",
            "steps": [
              {
                "color": "green",
                "value": null
              },
              {
                "color": "red",
                "value": 1
              }
            ]
          },
          "unit": "none"
        },
        "overrides": []
      },
      "gridPos": {
        "h": 3,
        "w": 4,
        "x": 12,
        "y": 57
      },
      "id": 29,
      "options": {
        "colorMode": "background",
        "graphMode": "none",
        "justifyMode": "auto",
        "orientation": "auto",
        "reduceOptions": {
          "calcs": [
            "lastNotNull"
          ],
          "fields": "",
          "values": false
        },
        "text": {},
        "textMode": "auto"
      },
      "pluginVersion": "8.5.13",
      "targets": [
        {
          "exemplar": true,
          "expr": "count(count by (name) (drbd_peerdevice_outofsync_bytes > 0)) OR on() vector(0)",
          "legendFormat": "",
          "refId": "A"
        }
      ],
      "title": "out-of-sync",
      "type": "stat"
    },
    {
      "datasource": {
        "uid": "${ds_prometheus}"
      },
      "description": "DRBD data out of sync with a peer",
      "fieldConfig": {
        "defaults": {
          "color": {
            "mode": "thresholds"
          },
          "mappings": [],
          "thresholds": {
            "mode": "absolute",
            "steps": [
              {
                "color": "green",
                "value": null
              },
              {
                "color": "red",
                "value": 1
              }
            ]
          },
          "unit": "bytes"
        },
        "overrides": []
      },
      "gridPos": {
        "h": 3,
        "w": 8,
        "x": 16,
        "y": 57
      },
      "id": 12,
      "options": {
        "colorMode": "value",
        "graphMode": "area",
        "justifyMode": "auto",
        "orientation": "auto",
        "reduceOptions": {
          "calcs": [
            "lastNotNull"
          ],
          "fields": "",
          "values": false
        },
        "text": {},
        "textMode": "auto"
      },
      "pluginVersion": "8.5.13",
      "targets": [
        {
          "exemplar": true,
          "expr": "sum(max by(name, volume) (drbd_peerdevice_outofsync_bytes > 0)) OR on() vector(0)",
          "legendFormat": "",
          "refId": "A"
        }
      ],
      "title": "out-of-sync data",
      "type": "stat"
    },
    {
      "datasource": {
        "uid": "${ds_prometheus}"
      },
      "fieldConfig": {
        "defaults": {
          "color": {
            "mode": "thresholds"
          },
          "custom": {
            "align": "auto",
            "displayMode": "auto",
            "filterable": false,
            "inspect": false
          },
          "mappings": [
            {
              "options": {
                "1": {
                  "text": "No"
                }
              },
              "type": "value"
            }
          ],
          "thresholds": {
            "mode": "absolute",
            "steps": [
              {
                "color": "green",
                "value": null
              },
              {
                "color": "red",
                "value": 1
              }
            ]
          }
        },
        "overrides": []
      },
      "gridPos": {
        "h": 8,
        "w": 12,
        "x": 0,
        "y": 60
      },
      "id": 22,
      "options": {
        "footer": {
          "fields": "",
          "reducer": [
            "sum"
          ],
          "show": false
        },
        "frameIndex": 0,
        "showHeader": true,
        "sortBy": [
          {
            "desc": false,
            "displayName": "drbd_connection_state"
          }
        ]
      },
      "pluginVersion": "8.5.13",
      "targets": [
        {
          "exemplar": true,
          "expr": "drbd_connection_state{drbd_connection_state!=\"UpToDate\", drbd_connection_state!=\"Connected\", node=~\"$node\"} == 1",
          "format": "table",
          "instant": true,
          "intervalFactor": 1,
          "legendFormat": "",
          "refId": "A"
        }
      ],
      "title": "Disconnected DRBD Resources",
      "transformations": [
        {
          "id": "merge",
          "options": {}
        },
        {
          "id": "organize",
          "options": {
            "excludeByName": {
              "Time": true,
              "Value": true,
              "__name__": true,
              "instance": true,
              "job": true,
              "name": false,
              "peer_node_id": true,
              "tier": true
            },
            "indexByName": {
              "Time": 1,
              "Value": 10,
              "__name__": 2,
              "conn_name": 5,
              "drbd_connection_state": 4,
              "instance": 6,
              "job": 7,
              "name": 0,
              "node": 3,
              "peer_node_id": 8,
              "tier": 9
            },
            "renameByName": {
              "Value #A": "Quorum?",
              "conn_name": "Remote Node",
              "drbd_connection_state": "State",
              "instance": "Instance",
              "job": "",
              "name": "DRBD Resource",
              "node": "Node",
              "peer_node_id": ""
            }
          }
        }
      ],
      "type": "table"
    },
    {
      "datasource": {
        "type": "prometheus",
        "uid": "${ds_prometheus}"
      },
      "fieldConfig": {
        "defaults": {
          "color": {
            "mode": "thresholds"
          },
          "custom": {
            "align": "auto",
            "displayMode": "auto",
            "filterable": false,
            "inspect": false
          },
          "mappings": [],
          "thresholds": {
            "mode": "absolute",
            "steps": [
              {
                "color": "green",
                "value": null
              }
            ]
          },
          "unit": "bytes"
        },
        "overrides": [
          {
            "matcher": {
              "id": "byName",
              "options": "DRBD Resource"
            },
            "properties": [
              {
                "id": "custom.width"
              }
            ]
          },
          {
            "matcher": {
              "id": "byName",
              "options": "Host"
            },
            "properties": [
              {
                "id": "custom.width"
              }
            ]
          },
          {
            "matcher": {
              "id": "byName",
              "options": "Out of Sync"
            },
            "properties": [
              {
                "id": "custom.width",
                "value": 93
              }
            ]
          }
        ]
      },
      "gridPos": {
        "h": 8,
        "w": 12,
        "x": 12,
        "y": 60
      },
      "id": 16,
      "options": {
        "footer": {
          "fields": "",
          "reducer": [
            "sum"
          ],
          "show": false
        },
        "frameIndex": 0,
        "showHeader": true,
        "sortBy": []
      },
      "pluginVersion": "8.5.13",
      "targets": [
        {
          "datasource": {
            "type": "prometheus",
            "uid": "P0D6E4079E36703EB"
          },
          "exemplar": false,
          "expr": "sum(drbd_peerdevice_outofsync_bytes) by(name, node) > 0",
          "format": "table",
          "hide": false,
          "instant": true,
          "legendFormat": "",
          "refId": "A"
        }
      ],
      "title": "DRBD Resources Out of Sync",
      "transformations": [
        {
          "id": "organize",
          "options": {
            "excludeByName": {
              "Time": true
            },
            "indexByName": {
              "Time": 0,
              "Value": 3,
              "name": 1,
              "node": 2
            },
            "renameByName": {
              "Time": "",
              "Value": "Out of Sync",
              "instance": "Host",
              "name": "DRBD Resource",
              "node": "Node"
            }
          }
        },
        {
          "id": "sortBy",
          "options": {
            "fields": {},
            "sort": [
              {
                "desc": true,
                "field": "Out of Sync"
              }
            ]
          }
        }
      ],
      "type": "table"
    },
    {
      "datasource": {
        "uid": "${ds_prometheus}"
      },
      "fieldConfig": {
        "defaults": {
          "color": {
            "mode": "thresholds"
          },
          "custom": {
            "align": "auto",
            "displayMode": "auto",
            "filterable": false,
            "inspect": false
          },
          "mappings": [
            {
              "options": {
                "1": {
                  "text": "No"
                }
              },
              "type": "value"
            }
          ],
          "thresholds": {
            "mode": "absolute",
            "steps": [
              {
                "color": "green",
                "value": null
              },
              {
                "color": "red",
                "value": 1
              }
            ]
          }
        },
        "overrides": []
      },
      "gridPos": {
        "h": 8,
        "w": 12,
        "x": 0,
        "y": 68
      },
      "id": 31,
      "options": {
        "footer": {
          "fields": "",
          "reducer": [
            "sum"
          ],
          "show": false
        },
        "frameIndex": 0,
        "showHeader": true
      },
      "pluginVersion": "8.5.13",
      "targets": [
        {
          "exemplar": true,
          "expr": "count(drbd_device_quorum == 0) by(node, name)",
          "format": "table",
          "instant": true,
          "intervalFactor": 1,
          "legendFormat": "",
          "refId": "A"
        }
      ],
      "title": "DRBD Resources Without Quorum",
      "transformations": [
        {
          "id": "merge",
          "options": {}
        },
        {
          "id": "organize",
          "options": {
            "excludeByName": {
              "Time": true,
              "Value": true
            },
            "indexByName": {},
            "renameByName": {
              "Value #A": "Quorum?",
              "instance": "Instance",
              "name": "DRBD Resource",
              "node": "Node"
            }
          }
        }
      ],
      "type": "table"
    },
    {
      "datasource": {
        "uid": "${ds_prometheus}"
      },
      "fieldConfig": {
        "defaults": {
          "color": {
            "mode": "thresholds"
          },
          "custom": {
            "align": "auto",
            "displayMode": "auto",
            "filterable": false,
            "inspect": false
          },
          "mappings": [
            {
              "options": {
                "1": {
                  "text": "No"
                }
              },
              "type": "value"
            }
          ],
          "thresholds": {
            "mode": "absolute",
            "steps": [
              {
                "color": "green",
                "value": null
              },
              {
                "color": "red",
                "value": 1
              }
            ]
          }
        },
        "overrides": []
      },
      "gridPos": {
        "h": 8,
        "w": 12,
        "x": 12,
        "y": 68
      },
      "id": 30,
      "options": {
        "footer": {
          "fields": "",
          "reducer": [
            "sum"
          ],
          "show": false
        },
        "frameIndex": 0,
        "showHeader": true
      },
      "pluginVersion": "8.5.13",
      "targets": [
        {
          "exemplar": true,
          "expr": "count(drbd_device_unintentionaldiskless == 1) by(node, name, minor)",
          "format": "table",
          "instant": true,
          "intervalFactor": 1,
          "legendFormat": "",
          "refId": "A"
        }
      ],
      "title": "DRBD Resources with Storage Failure",
      "transformations": [
        {
          "id": "merge",
          "options": {}
        },
        {
          "id": "organize",
          "options": {
            "excludeByName": {
              "Time": true,
              "Value": true
            },
            "indexByName": {
              "Time": 0,
              "Value": 4,
              "minor": 3,
              "name": 1,
              "node": 2
            },
            "renameByName": {
              "Value": "",
              "Value #A": "Quorum?",
              "instance": "Instance",
              "minor": "Minor",
              "name": "DRBD Resource",
              "node": "Node"
            }
          }
        }
      ],
      "type": "table"
    }
  ],
  "refresh": "30s",
  "schemaVersion": 36,
  "style": "dark",
  "tags": [],
  "templating": {
    "list": [
      {
        "current": {
          "selected": false,
          "text": "default",
          "value": "default"
        },
        "hide": 0,
        "includeAll": false,
        "label": "Prometheus",
        "multi": false,
        "name": "ds_prometheus",
        "options": [],
        "query": "prometheus",
        "queryValue": "",
        "refresh": 1,
        "regex": "",
        "skipUrlSync": false,
        "type": "datasource"
      },
      {
        "current": {
          "selected": true,
          "text": [
            "All"
          ],
          "value": [
            "$__all"
          ]
        },
        "datasource": {
          "type": "prometheus",
          "uid": "${ds_prometheus}"
        },
        "definition": "label_values(linstor_node_state{nodetype=\"SATELLITE\"}, node)",
        "hide": 0,
        "includeAll": true,
        "multi": true,
        "name": "node",
        "options": [],
        "query": {
          "query": "label_values(linstor_node_state{nodetype=\"SATELLITE\"}, node)",
          "refId": "StandardVariableQuery"
        },
        "refresh": 2,
        "regex": "",
        "skipUrlSync": false,
        "sort": 0,
        "tagValuesQuery": "",
        "tagsQuery": "",
        "type": "query",
        "useTags": false
      }
    ]
  },
  "time": {
    "from": "now-3h",
    "to": "now"
  },
  "timepicker": {},
  "timezone": "",
  "title": "LINSTOR / DRBD",
  "uid": "f_tZtVlMz",
  "version": 21,
  "weekStart": ""
}
